README.md
setup.py
MakeLog/make_log.py
MakeLog.egg-info/PKG-INFO
MakeLog.egg-info/SOURCES.txt
MakeLog.egg-info/dependency_links.txt
MakeLog.egg-info/top_level.txt