Metadata-Version: 1.0
Name: MakeLog
Version: 1.1b0
Summary: 
Home-page: UNKNOWN
Author: Darryl lane
Author-email: DarrylLane101@gmail.com
License: LICENSE
Platform: UNKNOWN
